twickster
