Metadata-Version: 2.1
Name: twickster
Version: 1.0.1
Summary: Unofficial Python Twitter API
Home-page: https://github.com/mokoshalb/twickster/
Author: Okoya Usman
Author-email: usmanokoya10@gmail.com
Keywords: twickster,python-twitter,Twitter,TwitterAPI,python-twitter-wrapper
Requires-Python: >=3.6
